_ldap.pyd
ldapurl.py
ldapurl.pyo
ldif.py
ldif.pyo
slapdtest.py
slapdtest.pyo
ldap/__init__.py
ldap/__init__.pyo
ldap/async.py
ldap/async.pyo
ldap/cidict.py
ldap/cidict.pyo
ldap/dn.py
ldap/dn.pyo
ldap/filter.py
ldap/filter.pyo
ldap/functions.py
ldap/functions.pyo
ldap/ldapobject.py
ldap/ldapobject.pyo
ldap/logger.py
ldap/logger.pyo
ldap/modlist.py
ldap/modlist.pyo
ldap/pkginfo.py
ldap/pkginfo.pyo
ldap/resiter.py
ldap/resiter.pyo
ldap/sasl.py
ldap/sasl.pyo
ldap/syncrepl.py
ldap/syncrepl.pyo
ldap/controls/__init__.py
ldap/controls/__init__.pyo
ldap/controls/deref.py
ldap/controls/deref.pyo
ldap/controls/libldap.py
ldap/controls/libldap.pyo
ldap/controls/openldap.py
ldap/controls/openldap.pyo
ldap/controls/ppolicy.py
ldap/controls/ppolicy.pyo
ldap/controls/psearch.py
ldap/controls/psearch.pyo
ldap/controls/pwdpolicy.py
ldap/controls/pwdpolicy.pyo
ldap/controls/readentry.py
ldap/controls/readentry.pyo
ldap/controls/sessiontrack.py
ldap/controls/sessiontrack.pyo
ldap/controls/simple.py
ldap/controls/simple.pyo
ldap/controls/sss.py
ldap/controls/sss.pyo
ldap/extop/__init__.py
ldap/extop/__init__.pyo
ldap/extop/dds.py
ldap/extop/dds.pyo
ldap/schema/__init__.py
ldap/schema/__init__.pyo
ldap/schema/models.py
ldap/schema/models.pyo
ldap/schema/subentry.py
ldap/schema/subentry.pyo
ldap/schema/tokenizer.py
ldap/schema/tokenizer.pyo
python_ldap-2.5.1.data/data/Lib/site-packages/ldap/LICENSE-OpenLDAP
python_ldap-2.5.1.data/data/Lib/site-packages/ldap/LICENSE-OpenSSL
python_ldap-2.5.1.data/data/Lib/site-packages/ldap/LICENSE-heimdal
python_ldap-2.5.1.data/data/Lib/site-packages/ldap/LICENSE-sasl
python_ldap-2.5.1.dist-info/DESCRIPTION.rst
python_ldap-2.5.1.dist-info/METADATA
python_ldap-2.5.1.dist-info/RECORD
python_ldap-2.5.1.dist-info/WHEEL
python_ldap-2.5.1.dist-info/metadata.json
python_ldap-2.5.1.dist-info/top_level.txt
