Metadata-Version: 2.0
Name: python-ldap
Version: 2.5.1
Summary: Python modules for implementing LDAP clients
Home-page: https://www.python-ldap.org/
Author: python-ldap project
Author-email: python-ldap@python.org
License: Python style
Download-URL: https://pypi.python.org/pypi/python-ldap/
Platform: UNKNOWN
Classifier: Development Status :: 5 - Production/Stable
Classifier: Intended Audience :: Developers
Classifier: Intended Audience :: System Administrators
Classifier: Operating System :: OS Independent
Classifier: Operating System :: MacOS :: MacOS X
Classifier: Operating System :: Microsoft :: Windows
Classifier: Operating System :: POSIX
Classifier: Programming Language :: C
Classifier: Programming Language :: Python
Classifier: Programming Language :: Python :: 2
Classifier: Topic :: Database
Classifier: Topic :: Internet
Classifier: Topic :: Software Development :: Libraries :: Python Modules
Classifier: Topic :: System :: Systems Administration :: Authentication/Directory :: LDAP
Classifier: License :: OSI Approved :: Python Software Foundation License
Requires-Dist: setuptools
